simple_torn_wrapper/Wrapper.py
simple_torn_wrapper/__init__.py
simple_torn_wrapper-0.0.4.dist-info/LICENSE
simple_torn_wrapper-0.0.4.dist-info/METADATA
simple_torn_wrapper-0.0.4.dist-info/WHEEL
simple_torn_wrapper-0.0.4.dist-info/top_level.txt
simple_torn_wrapper-0.0.4.dist-info/RECORD
