Metadata-Version: 2.1
Name: simple-torn-wrapper
Version: 0.0.4
Summary: A simple wrapper for the Torn API
Home-page: https://github.com/SolitudalDeveloper/SimpleTorn
Author: Solitudal Developer
Author-email: innominatusofficial@gmail.com
License: UNKNOWN
Project-URL: Bug Tracker, https://github.com/SolitudalDeveloper/SimpleTorn/issues
Platform: UNKNOWN
Classifier: Programming Language :: Python :: 3
Classifier: License :: OSI Approved :: MIT License
Classifier: Operating System :: OS Independent
Requires-Python: >=3.9
Requires-Dist: requests
